[["achievements",{"version":2,"data":{"vecHighlight":[{"strID":"BG3_Quest04","strName":"All's Well That Ends Well","strDescription":"Finish the game (with a heartfelt 'thank you!' from Larian Studios).","bAchieved":true,"rtUnlocked":1694881516,"strImage":"https://cdn.steamstatic.com/steamcommunity/public/images/apps/1086940/ecd435323119579216ebcffebae690ae2e5c13eb.jpg","bHidden":true,"flMinProgress":0,"flCurrentProgress":0,"flMaxProgress":0,"flAchieved":22.799999237060547},{"strID":"BG3_Quest06","strName":"Hero of the Forgotten Realms","strDescription":"Save the realms: destroy the Absolute once and for all.","bAchieved":true,"rtUnlocked":1694881516,"strImage":"https://cdn.steamstatic.com/steamcommunity/public/images/apps/1086940/7648f980938af51c9f1378ec1171673fc8d8d0b4.jpg","bHidden":true,"flMinProgress":0,"flCurrentProgress":0,"flMaxProgress":0,"flAchieved":24.299999237060547},{"strID":"BG3_Quest39","strName":"Interfectorem Draconis","strDescription":"Kill the red dragon in the Upper City.","bAchieved":true,"rtUnlocked":1694878125,"strImage":"https://cdn.steamstatic.com/steamcommunity/public/images/apps/1086940/3d7168b924848191b7914dfef2116d96e249bbf0.jpg","bHidden":true,"flMinProgress":0,"flCurrentProgress":0,"flMaxProgress":0,"flAchieved":16.700000762939453},{"strID":"BG3_Quest38","strName":"First Blood","strDescription":"Kill Orin while her cultists are performing their ritual chant.","bAchieved":true,"rtUnlocked":1694869461,"strImage":"https://cdn.steamstatic.com/steamcommunity/public/images/apps/1086940/bd574766f04f7d47c4bc0639344ef0561e0cc310.jpg","bHidden":true,"flMinProgress":0,"flCurrentProgress":0,"flMaxProgress":0,"flAchieved":19.299999237060547},{"strID":"BG3_Quest40","strName":"Crash Landing","strDescription":"In the Wyrmway, wait until the dragon is mid-flight, then knock it out of the sky - KAPOW.","bAchieved":true,"rtUnlocked":1694859132,"strImage":"https://cdn.steamstatic.com/steamcommunity/public/images/apps/1086940/92eff966f9b0d8eb71b9529a0b74e6c075bff2f9.jpg","bHidden":false,"flMinProgress":0,"flCurrentProgress":0,"flMaxProgress":0,"flAchieved":6.900000095367432},{"strID":"BG3_Quest37","strName":"Fancy Footwork","strDescription":"Defeat Gortash in Wyrm's Rock without activating any traps.","bAchieved":true,"rtUnlocked":1694794389,"strImage":"https://cdn.steamstatic.com/steamcommunity/public/images/apps/1086940/ae3adaf3d6f530e91b33975acdd30e7f7031437a.jpg","bHidden":false,"flMinProgress":0,"flCurrentProgress":0,"flMaxProgress":0,"flAchieved":5},{"strID":"BG3_Quest27","strName":"Kill Two Birds With One Gnome","strDescription":"Use one enemy as an improvised weapon against another. ","bAchieved":true,"rtUnlocked":1694681725,"strImage":"https://cdn.steamstatic.com/steamcommunity/public/images/apps/1086940/4d651ac095d988353bb73662b37b4c9f049a8ea2.jpg","bHidden":false,"flMinProgress":0,"flCurrentProgress":0,"flMaxProgress":0,"flAchieved":10.100000381469727},{"strID":"BG3_Quest16","strName":"Jack-of-all-Trades","strDescription":"Multiclass into every class in one playthrough without asking Withers to change your character.","bAchieved":true,"rtUnlocked":1694597871,"strImage":"https://cdn.steamstatic.com/steamcommunity/public/images/apps/1086940/5f62e2f146d67732fe8a8dc02a322cf1f3a2c600.jpg","bHidden":false,"flMinProgress":0,"flCurrentProgress":0,"flMaxProgress":0,"flAchieved":2.700000047683716},{"strID":"BG3_Quest17","strName":"Homebrewer","strDescription":"Create three unique alchemical solutions in a single playthrough - bottoms up! ","bAchieved":true,"rtUnlocked":1694024653,"strImage":"https://cdn.steamstatic.com/steamcommunity/public/images/apps/1086940/6d417ad8e5789c17018533c40471d29a73d2228b.jpg","bHidden":false,"flMinProgress":0,"flCurrentProgress":3,"flMaxProgress":3,"flAchieved":30.600000381469727},{"strID":"BG3_Quest26","strName":"Mind Blown","strDescription":"Romance the Emperor.","bAchieved":true,"rtUnlocked":1693732735,"strImage":"https://cdn.steamstatic.com/steamcommunity/public/images/apps/1086940/815c476427127cf4fed9cfb4bf7a0b0290e01733.jpg","bHidden":true,"flMinProgress":0,"flCurrentProgress":0,"flMaxProgress":0,"flAchieved":12.699999809265137},{"strID":"BG3_Quest51","strName":"Loophole","strDescription":"Break Wyll's pact with Mizora.","bAchieved":true,"rtUnlocked":1693731992,"strImage":"https://cdn.steamstatic.com/steamcommunity/public/images/apps/1086940/70972fff002e080bdd5b86295f0241448bfe2481.jpg","bHidden":true,"flMinProgress":0,"flCurrentProgress":0,"flMaxProgress":0,"flAchieved":24.100000381469727},{"strID":"BG3_Quest41","strName":"Bottoms Up","strDescription":"Long Rest using only alcohol - a time-honoured dwarven tradition. ","bAchieved":true,"rtUnlocked":1693329530,"strImage":"https://cdn.steamstatic.com/steamcommunity/public/images/apps/1086940/a9ee13ee9d602b4f3b3957546e3df09117050eae.jpg","bHidden":false,"flMinProgress":0,"flCurrentProgress":0,"flMaxProgress":0,"flAchieved":30.5}],"vecUnachieved":[{"strID":"BG3_Quest30","strName":"Fists of Fury","strDescription":"Kill a character with an Unarmed Strike.","strImage":"https://cdn.steamstatic.com/steamcommunity/public/images/apps/1086940/5d6a1f80a5e816ee90bab4d96656219e30903fb5.jpg","bAchieved":false,"rtUnlocked":0,"flAchieved":40.599998474121094,"flMinProgress":0,"flCurrentProgress":0,"flMaxProgress":0},{"strID":"BG3_Quest34","strName":"Non-Invasive Procedure","strDescription":"Kill the Surgeon before he performs surgery on you in combat.","strImage":"https://cdn.steamstatic.com/steamcommunity/public/images/apps/1086940/30544be3da4df4a803371dfee3bf211abae8f5a5.jpg","bAchieved":false,"rtUnlocked":0,"flAchieved":23,"flMinProgress":0,"flCurrentProgress":0,"flMaxProgress":0},{"strID":"BG3_Quest15","strName":"Outsourcing","strDescription":"Recruit a hireling. You can befriend them or use them as cannon-fodder - we won't judge.","strImage":"https://cdn.steamstatic.com/steamcommunity/public/images/apps/1086940/03158bd6dfa768f111c3666c46b39f77b2d3ca61.jpg","bAchieved":false,"rtUnlocked":0,"flAchieved":18,"flMinProgress":0,"flCurrentProgress":0,"flMaxProgress":0},{"strID":"BG3_Quest53","strName":"Critical Hit","strDescription":"Complete the game in Tactician mode.","strImage":"https://cdn.steamstatic.com/steamcommunity/public/images/apps/1086940/d92b5372fbf62e667c33d109edc0a28a6aa12383.jpg","bAchieved":false,"rtUnlocked":0,"flAchieved":5,"flMinProgress":0,"flCurrentProgress":0,"flMaxProgress":0},{"strID":"BG3_Quest44","strName":"Punch Drunk","strDescription":"Defeat twenty opponents while drunk - down them.","strImage":"https://cdn.steamstatic.com/steamcommunity/public/images/apps/1086940/72d53386ef52ab6412d935ec89de7c1565474924.jpg","bAchieved":false,"rtUnlocked":0,"flAchieved":2.4000000953674316,"flMinProgress":0,"flCurrentProgress":0,"flMaxProgress":20},{"strID":"BG3_Quest28","strName":"Busker","strDescription":"Earn a hundred gold from playing sweet, sweet music in a single playthrough. ","strImage":"https://cdn.steamstatic.com/steamcommunity/public/images/apps/1086940/dffac3c431ff07d705ae86cfad147f1a490b39be.jpg","bAchieved":false,"rtUnlocked":0,"flAchieved":2.0999999046325684,"flMinProgress":0,"flCurrentProgress":0,"flMaxProgress":100},{"strID":"BG3_Quest54","strName":"Foehammer","strDescription":"Complete the game in Honour mode.","strImage":"https://cdn.steamstatic.com/steamcommunity/public/images/apps/1086940/0812cb6a6b9da0a844295409c1baaef2e0a69c4d.jpg","bAchieved":false,"rtUnlocked":0,"flAchieved":2.0999999046325684,"flMinProgress":0,"flCurrentProgress":0,"flMaxProgress":0}],"vecAchievedHidden":[{"strID":"BG3_Quest02","strName":"The Plot Thickens","strDescription":"Leave Act I - for somewhere altogether darker.","strImage":"https://cdn.steamstatic.com/steamcommunity/public/images/apps/1086940/628cdbbfd2e731735e4817252ce6633bf3bcd8ed.jpg","bAchieved":true,"rtUnlocked":1691780283,"flAchieved":0},{"strID":"BG3_Quest03","strName":"The City Awaits","strDescription":"Leave Act II - Baldur's Gate is just over the horizon.","strImage":"https://cdn.steamstatic.com/steamcommunity/public/images/apps/1086940/3c6d05ff648b66925238963a658ee307e31ff870.jpg","bAchieved":true,"rtUnlocked":1692890106,"flAchieved":0},{"strID":"BG3_Quest04","strName":"All's Well That Ends Well","strDescription":"Finish the game (with a heartfelt 'thank you!' from Larian Studios).","strImage":"https://cdn.steamstatic.com/steamcommunity/public/images/apps/1086940/ecd435323119579216ebcffebae690ae2e5c13eb.jpg","bAchieved":true,"rtUnlocked":1694881516,"flAchieved":0},{"strID":"BG3_Quest06","strName":"Hero of the Forgotten Realms","strDescription":"Save the realms: destroy the Absolute once and for all.","strImage":"https://cdn.steamstatic.com/steamcommunity/public/images/apps/1086940/7648f980938af51c9f1378ec1171673fc8d8d0b4.jpg","bAchieved":true,"rtUnlocked":1694881516,"flAchieved":0},{"strID":"BG3_Quest11","strName":"Expand Your Mind","strDescription":"Consume a parasite and unlock a new power - is it meant to wriggle the whole way down?","strImage":"https://cdn.steamstatic.com/steamcommunity/public/images/apps/1086940/279a9b7a2d50b65b6b30a939bbceffd556bb10ff.jpg","bAchieved":true,"rtUnlocked":1691583244,"flAchieved":0},{"strID":"BG3_Quest20","strName":"Forged in Blood and Fire","strDescription":"Craft an item in the Adamantine Forge.","strImage":"https://cdn.steamstatic.com/steamcommunity/public/images/apps/1086940/a00e6ad2d3d84c4649654ce74a82cc2fa96cf3cf.jpg","bAchieved":true,"rtUnlocked":1691750587,"flAchieved":0},{"strID":"BG3_Quest23","strName":"Taking Blood","strDescription":"Steal the Blood of Lathander from underneath Rosymorn Monastery.","strImage":"https://cdn.steamstatic.com/steamcommunity/public/images/apps/1086940/cc1a63fce03ab5580530c8efcef4a86a46708a39.jpg","bAchieved":true,"rtUnlocked":1691774643,"flAchieved":0},{"strID":"BG3_Quest26","strName":"Mind Blown","strDescription":"Romance the Emperor.","strImage":"https://cdn.steamstatic.com/steamcommunity/public/images/apps/1086940/815c476427127cf4fed9cfb4bf7a0b0290e01733.jpg","bAchieved":true,"rtUnlocked":1693732735,"flAchieved":0},{"strID":"BG3_Quest32","strName":"Pest Control","strDescription":"Kill the Spider Matriarch before her eggs hatch - why do they have so many legs?","strImage":"https://cdn.steamstatic.com/steamcommunity/public/images/apps/1086940/f9353502a5d66c5160f1474c50c86c521e0481fa.jpg","bAchieved":true,"rtUnlocked":1691602463,"flAchieved":0},{"strID":"BG3_Quest36","strName":"No Free Lunches","strDescription":"Defeat the Apostle of Myrkul before it consumes any necromites.","strImage":"https://cdn.steamstatic.com/steamcommunity/public/images/apps/1086940/dadbc866606e4b4464fcdbf6684e3f2ec207ad73.jpg","bAchieved":true,"rtUnlocked":1692883064,"flAchieved":0},{"strID":"BG3_Quest38","strName":"First Blood","strDescription":"Kill Orin while her cultists are performing their ritual chant.","strImage":"https://cdn.steamstatic.com/steamcommunity/public/images/apps/1086940/bd574766f04f7d47c4bc0639344ef0561e0cc310.jpg","bAchieved":true,"rtUnlocked":1694869461,"flAchieved":0},{"strID":"BG3_Quest39","strName":"Interfectorem Draconis","strDescription":"Kill the red dragon in the Upper City.","strImage":"https://cdn.steamstatic.com/steamcommunity/public/images/apps/1086940/3d7168b924848191b7914dfef2116d96e249bbf0.jpg","bAchieved":true,"rtUnlocked":1694878125,"flAchieved":0},{"strID":"BG3_Quest46","strName":"Repairing the Weave","strDescription":"Stabilise Gale's Netherese orb.","strImage":"https://cdn.steamstatic.com/steamcommunity/public/images/apps/1086940/f202f039116ecee22d8aaacee24370a55f1983dd.jpg","bAchieved":true,"rtUnlocked":1691760051,"flAchieved":0},{"strID":"BG3_Quest47","strName":"The Lich-Queen's Wrath","strDescription":"Ally with Voss against the githyanki God-Queen. Good luck.","strImage":"https://cdn.steamstatic.com/steamcommunity/public/images/apps/1086940/7944771c84a4ee57b9332b25dfeb9a7c0dea1cb8.jpg","bAchieved":true,"rtUnlocked":1691779600,"flAchieved":0},{"strID":"BG3_Quest48","strName":"To Bloom in Darkest Night","strDescription":"Gift Shadowheart a night orchid - her favourite flower. Always knew she was a softie.","strImage":"https://cdn.steamstatic.com/steamcommunity/public/images/apps/1086940/f074708db163ec1cf253953b7fe4cc32e929657c.jpg","bAchieved":true,"rtUnlocked":1692303474,"flAchieved":0},{"strID":"BG3_Quest50","strName":"Just a Nibble","strDescription":"Let Astarion bite you at night - ouch.","strImage":"https://cdn.steamstatic.com/steamcommunity/public/images/apps/1086940/884c0f57453132979551b5053fd3f03bb8176038.jpg","bAchieved":true,"rtUnlocked":1691329879,"flAchieved":0},{"strID":"BG3_Quest51","strName":"Loophole","strDescription":"Break Wyll's pact with Mizora.","strImage":"https://cdn.steamstatic.com/steamcommunity/public/images/apps/1086940/70972fff002e080bdd5b86295f0241448bfe2481.jpg","bAchieved":true,"rtUnlocked":1693731992,"flAchieved":0}],"nTotal":54,"nAchieved":35}}]]