[["achievements",{"version":2,"data":{"vecHighlight":[{"strID":"BloodMist_4","strName":"Push Your Limits","strDescription":"Challenge Blood Mist 4","bAchieved":true,"rtUnlocked":1716391507,"strImage":"https://cdn.steamstatic.com/steamcommunity/public/images/apps/1188930/4c1d6477a67e7e90c12b4f45cfe82bf64f09b15e.jpg","bHidden":false,"flMinProgress":0,"flCurrentProgress":0,"flMaxProgress":0,"flAchieved":10.399999618530273},{"strID":"NEW_ACHIEVEMENT_4_7","strName":"Happiness within the Birdcage","strDescription":" ","bAchieved":true,"rtUnlocked":1716110015,"strImage":"https://cdn.steamstatic.com/steamcommunity/public/images/apps/1188930/daa9e2feed5e8bc16b6eeab7d3075fc9c84c8190.jpg","bHidden":true,"flMinProgress":0,"flCurrentProgress":0,"flMaxProgress":0,"flAchieved":14.899999618530273},{"strID":"NEW_ACHIEVEMENT_1_11","strName":"Fake Madness","strDescription":"Clear the game with Hein.","bAchieved":true,"rtUnlocked":1716072518,"strImage":"https://cdn.steamstatic.com/steamcommunity/public/images/apps/1188930/10c10bf5d758a218c1a27c863ecc882aedf6d2d0.jpg","bHidden":false,"flMinProgress":0,"flCurrentProgress":0,"flMaxProgress":0,"flAchieved":24.600000381469727},{"strID":"NEW_ACHIEVEMENT_1_18","strName":"That Sounds Perfect","strDescription":"Clear the game with Huz.","bAchieved":true,"rtUnlocked":1716072518,"strImage":"https://cdn.steamstatic.com/steamcommunity/public/images/apps/1188930/4714c9b40222d1d2d040584c1ca2a2ee1abea928.jpg","bHidden":false,"flMinProgress":0,"flCurrentProgress":0,"flMaxProgress":0,"flAchieved":19.200000762939453},{"strID":"NEW_ACHIEVEMENT_1_29","strName":"Momori☆Victory!","strDescription":"Clear the game with Momori.","bAchieved":true,"rtUnlocked":1716072518,"strImage":"https://cdn.steamstatic.com/steamcommunity/public/images/apps/1188930/1ded6814ee6796e35fc75e53403759bd5a941237.jpg","bHidden":false,"flMinProgress":0,"flCurrentProgress":0,"flMaxProgress":0,"flAchieved":8.800000190734863},{"strID":"BloodMist_3","strName":"Into the Abyss","strDescription":"Challenge Blood Mist 3","bAchieved":true,"rtUnlocked":1715781506,"strImage":"https://cdn.steamstatic.com/steamcommunity/public/images/apps/1188930/b3cd88406f1ba55ff05ec7613cdb266567027776.jpg","bHidden":false,"flMinProgress":0,"flCurrentProgress":0,"flMaxProgress":0,"flAchieved":15.699999809265137},{"strID":"NEW_ACHIEVEMENT_1_7","strName":"Parry Master","strDescription":"Clear the game with Lian.","bAchieved":true,"rtUnlocked":1715113223,"strImage":"https://cdn.steamstatic.com/steamcommunity/public/images/apps/1188930/a941e976d6026c3100be64704e3cbf47c682a7f1.jpg","bHidden":false,"flMinProgress":0,"flCurrentProgress":0,"flMaxProgress":0,"flAchieved":20.700000762939453},{"strID":"NEW_ACHIEVEMENT_1_9","strName":"Almighty Pressel...","strDescription":"Clear the game with Pressel.","bAchieved":true,"rtUnlocked":1715113223,"strImage":"https://cdn.steamstatic.com/steamcommunity/public/images/apps/1188930/ac60b24f19e3e3455b66d2016ececf22d5ff525c.jpg","bHidden":false,"flMinProgress":0,"flCurrentProgress":0,"flMaxProgress":0,"flAchieved":33.70000076293945},{"strID":"NEW_ACHIEVEMENT_1_20","strName":"War of Arrows","strDescription":"Clear the game with Johan","bAchieved":true,"rtUnlocked":1715113223,"strImage":"https://cdn.steamstatic.com/steamcommunity/public/images/apps/1188930/e361d2cb5d70dea59aa4177851ab10821f3af557.jpg","bHidden":false,"flMinProgress":0,"flCurrentProgress":0,"flMaxProgress":0,"flAchieved":22.5},{"strID":"NEW_ACHIEVEMENT_1_22","strName":"Power of Frost, Thunder, and Vodka","strDescription":"Clear the game with Ilya","bAchieved":true,"rtUnlocked":1715113223,"strImage":"https://cdn.steamstatic.com/steamcommunity/public/images/apps/1188930/97b94d47e3976cd4355104394c05f95db773eb58.jpg","bHidden":false,"flMinProgress":0,"flCurrentProgress":0,"flMaxProgress":0,"flAchieved":19.700000762939453},{"strID":"NEW_ACHIEVEMENT_4_6","strName":"Cutie of the Investigators","strDescription":"Become friends with 5 Investigators.","bAchieved":true,"rtUnlocked":1715104845,"strImage":"https://cdn.steamstatic.com/steamcommunity/public/images/apps/1188930/c00321b2402345e1a36593e88b226871ebe38437.jpg","bHidden":false,"flMinProgress":0,"flCurrentProgress":0,"flMaxProgress":0,"flAchieved":17.100000381469727},{"strID":"NEW_ACHIEVEMENT_1_5","strName":"Illusion Sword!","strDescription":"Clear the game with Azar.","bAchieved":true,"rtUnlocked":1712868368,"strImage":"https://cdn.steamstatic.com/steamcommunity/public/images/apps/1188930/a6a661c5d872e9b7c16c3e9531889c278a41093d.jpg","bHidden":false,"flMinProgress":0,"flCurrentProgress":0,"flMaxProgress":0,"flAchieved":22.200000762939453}],"vecUnachieved":[{"strID":"NEW_ACHIEVEMENT_1_17","strName":"Master Psychologist","strDescription":"Clear the game with Narhan.","strImage":"https://cdn.steamstatic.com/steamcommunity/public/images/apps/1188930/3bcf3775cf900aefab7840cc40ebd5ee9af195d2.jpg","bAchieved":false,"rtUnlocked":0,"flAchieved":23.799999237060547,"flMinProgress":0,"flCurrentProgress":0,"flMaxProgress":0},{"strID":"NEW_ACHIEVEMENT_1_19","strName":"Perfect Rotation","strDescription":"Clear the game with Selena & Helia.","strImage":"https://cdn.steamstatic.com/steamcommunity/public/images/apps/1188930/e86e3a2acb7e650ef6c2665d0e40684147fab2c6.jpg","bAchieved":false,"rtUnlocked":0,"flAchieved":15.100000381469727,"flMinProgress":0,"flCurrentProgress":0,"flMaxProgress":0},{"strID":"NEW_ACHIEVEMENT_1_4","strName":"Clear Expert Difficulty","strDescription":"Clear the game on Expert Difficulty.","strImage":"https://cdn.steamstatic.com/steamcommunity/public/images/apps/1188930/20fed96ac13e2558ef5958e31b4fbd074e6abfb4.jpg","bAchieved":false,"rtUnlocked":0,"flAchieved":14.600000381469727,"flMinProgress":0,"flCurrentProgress":0,"flMaxProgress":0},{"strID":"NEW_ACHIEVEMENT_1_28","strName":"Leap Through Time","strDescription":"Clear the game with Leryn.","strImage":"https://cdn.steamstatic.com/steamcommunity/public/images/apps/1188930/aa02b6d1fcbd442674b387dc4749921a0afef032.jpg","bAchieved":false,"rtUnlocked":0,"flAchieved":13.899999618530273,"flMinProgress":0,"flCurrentProgress":0,"flMaxProgress":0},{"strID":"NEW_ACHIEVEMENT_1_16","strName":"*Burps*","strDescription":"Clear the game with Phoenix.","strImage":"https://cdn.steamstatic.com/steamcommunity/public/images/apps/1188930/ffab13797cbc95055a4d09e9857b0aa714af9e96.jpg","bAchieved":false,"rtUnlocked":0,"flAchieved":10.800000190734863,"flMinProgress":0,"flCurrentProgress":0,"flMaxProgress":0},{"strID":"NEW_ACHIEVEMENT_1_26","strName":"Lone but not Lonely Wolf","strDescription":" ","strImage":"https://cdn.steamstatic.com/steamcommunity/public/images/apps/1188930/f090adcba6b363c30ead05801637c0413a5a9152.jpg","bAchieved":false,"rtUnlocked":0,"flAchieved":9.699999809265137,"flMinProgress":0,"flCurrentProgress":0,"flMaxProgress":0},{"strID":"BloodMist_5","strName":"Blood Mist Master","strDescription":"Clear Blood Mist 4","strImage":"https://cdn.steamstatic.com/steamcommunity/public/images/apps/1188930/331a6a40d94abd3ac3f1bda105614d8aca8a6a52.jpg","bAchieved":false,"rtUnlocked":0,"flAchieved":9.199999809265137,"flMinProgress":0,"flCurrentProgress":0,"flMaxProgress":0},{"strID":"NEW_ACHIEVEMENT_1_23","strName":"Lucy's Adventure","strDescription":" ","strImage":"https://cdn.steamstatic.com/steamcommunity/public/images/apps/1188930/97a5c4f916db93cd858c88f4d8e907625e4855b5.jpg","bAchieved":false,"rtUnlocked":0,"flAchieved":8.699999809265137,"flMinProgress":0,"flCurrentProgress":0,"flMaxProgress":0},{"strID":"NEW_ACHIEVEMENT_1_24","strName":"All Random","strDescription":" ","strImage":"https://cdn.steamstatic.com/steamcommunity/public/images/apps/1188930/c9d8b99ea15c01817fe5602841c45f73157fcc73.jpg","bAchieved":false,"rtUnlocked":0,"flAchieved":6.300000190734863,"flMinProgress":0,"flCurrentProgress":0,"flMaxProgress":0},{"strID":"NEW_ACHIEVEMENT_1_25","strName":"Everything is Once","strDescription":" ","strImage":"https://cdn.steamstatic.com/steamcommunity/public/images/apps/1188930/0409ea79e2b2b03b1d2b7fb32337e0e36621f4fb.jpg","bAchieved":false,"rtUnlocked":0,"flAchieved":5.900000095367432,"flMinProgress":0,"flCurrentProgress":0,"flMaxProgress":0},{"strID":"NEW_ACHIEVEMENT_1_27","strName":"Quick Building","strDescription":" ","strImage":"https://cdn.steamstatic.com/steamcommunity/public/images/apps/1188930/15450656606e1dc90eeda9f073ddce1f0e73b4b7.jpg","bAchieved":false,"rtUnlocked":0,"flAchieved":4.099999904632568,"flMinProgress":0,"flCurrentProgress":0,"flMaxProgress":0},{"strID":"NEW_ACHIEVEMENT_4_10","strName":"Everyone’s Friend","strDescription":"Become friends with every Investigator.","strImage":"https://cdn.steamstatic.com/steamcommunity/public/images/apps/1188930/4f1188c34b94d47b5352cbecf01f206c1c56db87.jpg","bAchieved":false,"rtUnlocked":0,"flAchieved":2.799999952316284,"flMinProgress":0,"flCurrentProgress":0,"flMaxProgress":0}],"vecAchievedHidden":[{"strID":"NEW_ACHIEVEMENT_4_7","strName":"Happiness within the Birdcage","strDescription":" ","strImage":"https://cdn.steamstatic.com/steamcommunity/public/images/apps/1188930/daa9e2feed5e8bc16b6eeab7d3075fc9c84c8190.jpg","bAchieved":true,"rtUnlocked":1716110015,"flAchieved":0}],"nTotal":40,"nAchieved":24}}]]