[["achievements",{"version":2,"data":{"vecHighlight":[],"vecUnachieved":[{"strID":"ACHIEVEMENT_3","strName":"It's just the beginning","strDescription":"Complete all side activities on intro sequence ship.","strImage":"https://cdn.steamstatic.com/steamcommunity/public/images/apps/1467450/a6a285b28086eab8856fb8c4f8f6524d9a4ee332.jpg","bAchieved":false,"rtUnlocked":0,"flAchieved":48.79999923706055,"flMinProgress":0,"flCurrentProgress":0,"flMaxProgress":0},{"strID":"ACHIEVEMENT_7","strName":"Wanderer","strDescription":"Use all forms of fast travel.","strImage":"https://cdn.steamstatic.com/steamcommunity/public/images/apps/1467450/b24fbac77b3cbc6e9d1e0e7c899093c5f4f4130c.jpg","bAchieved":false,"rtUnlocked":0,"flAchieved":44.599998474121094,"flMinProgress":0,"flCurrentProgress":0,"flMaxProgress":0},{"strID":"ACHIEVEMENT_30","strName":"Best friend","strDescription":"Pet a dog.","strImage":"https://cdn.steamstatic.com/steamcommunity/public/images/apps/1467450/bfb1dce741190b40d974ba2392ef579a216e1dca.jpg","bAchieved":false,"rtUnlocked":0,"flAchieved":40.5,"flMinProgress":0,"flCurrentProgress":0,"flMaxProgress":0},{"strID":"ACHIEVEMENT_12","strName":"How will it be in Khorinis?","strDescription":"Create something that was meant to be a little joke.","strImage":"https://cdn.steamstatic.com/steamcommunity/public/images/apps/1467450/5c9490645c691ff7f61c319fcb6bef3e75e08591.jpg","bAchieved":false,"rtUnlocked":0,"flAchieved":39.70000076293945,"flMinProgress":0,"flCurrentProgress":0,"flMaxProgress":0},{"strID":"ACHIEVEMENT_20","strName":"Self-sufficient","strDescription":"Convert heavy branches to 50 arrows or bolts.","strImage":"https://cdn.steamstatic.com/steamcommunity/public/images/apps/1467450/0ce620887eaf142a7a97df0bbe0420ca2d70afec.jpg","bAchieved":false,"rtUnlocked":0,"flAchieved":39,"flMinProgress":0,"flCurrentProgress":0,"flMaxProgress":50},{"strID":"ACHIEVEMENT_10","strName":"Arena master","strDescription":"Prove that there is no greater warrior from you, even when everyone’s watching.","strImage":"https://cdn.steamstatic.com/steamcommunity/public/images/apps/1467450/9f748d34220a6a086743af8a4a89997712aafa0e.jpg","bAchieved":false,"rtUnlocked":0,"flAchieved":38.70000076293945,"flMinProgress":0,"flCurrentProgress":0,"flMaxProgress":0},{"strID":"ACHIEVEMENT_16","strName":"Valley Of Mines","strDescription":"Mine iron, gold, silver and magic ore.","strImage":"https://cdn.steamstatic.com/steamcommunity/public/images/apps/1467450/3142574d1570ee4e66d57703d0d1af79866fce4b.jpg","bAchieved":false,"rtUnlocked":0,"flAchieved":37.599998474121094,"flMinProgress":0,"flCurrentProgress":0,"flMaxProgress":0},{"strID":"ACHIEVEMENT_28","strName":"Bounty hunter","strDescription":"Complete 6 bounties from wanted posters.","strImage":"https://cdn.steamstatic.com/steamcommunity/public/images/apps/1467450/7a6f7f26b3c6989b9f47f31eca6aca6e4cd5b535.jpg","bAchieved":false,"rtUnlocked":0,"flAchieved":36.900001525878906,"flMinProgress":0,"flCurrentProgress":0,"flMaxProgress":6},{"strID":"ACHIEVEMENT_27","strName":"Our house, in the middle of our street","strDescription":"Own a house.","strImage":"https://cdn.steamstatic.com/steamcommunity/public/images/apps/1467450/a82537a35bb930ff312a232fdbcbf4201e9b6428.jpg","bAchieved":false,"rtUnlocked":0,"flAchieved":36.5,"flMinProgress":0,"flCurrentProgress":0,"flMaxProgress":0},{"strID":"ACHIEVEMENT_32","strName":"The Beast","strDescription":"Defeat the Beast.","strImage":"https://cdn.steamstatic.com/steamcommunity/public/images/apps/1467450/d6a7faa9fd03f2cf79318dff822d8cc60fb8accf.jpg","bAchieved":false,"rtUnlocked":0,"flAchieved":35.599998474121094,"flMinProgress":0,"flCurrentProgress":0,"flMaxProgress":0},{"strID":"ACHIEVEMENT_14","strName":"Forsaken Gods","strDescription":"Interact with the shrine of every god.","strImage":"https://cdn.steamstatic.com/steamcommunity/public/images/apps/1467450/b0ed477cb723c21bd36044d4bdc2506895fee5fb.jpg","bAchieved":false,"rtUnlocked":0,"flAchieved":34.20000076293945,"flMinProgress":0,"flCurrentProgress":0,"flMaxProgress":0},{"strID":"ACHIEVEMENT_15","strName":"Trial of the Grasses","strDescription":"Be under the effect of three time potions at the same time.","strImage":"https://cdn.steamstatic.com/steamcommunity/public/images/apps/1467450/cc567576a720cc2405152dff0f6b5a8ecff61811.jpg","bAchieved":false,"rtUnlocked":0,"flAchieved":32.79999923706055,"flMinProgress":0,"flCurrentProgress":0,"flMaxProgress":0}],"vecAchievedHidden":[],"nTotal":40,"nAchieved":0}}],["achievementmap",{"version":5,"data":"[]"}],["usernews",{"version":5,"data":[]}],["gameactivity",{"version":5,"data":[]}],["socialmedia",{"version":3,"data":[]}],["associations",{"version":2,"data":{"rgDevelopers":[{"strName":"The Chronicles Of Myrtana Team","strURL":"https://store.steampowered.com/developer/TheChroniclesOfMyrtanaTeam"}],"rgPublishers":[{"strName":"The Chronicles Of Myrtana Team","strURL":"https://store.steampowered.com/publisher/TheChroniclesOfMyrtanaTeam"}],"rgFranchises":[]}}]]