[["achievements",{"version":2,"data":{"vecHighlight":[{"strID":"ACH00","strName":"Sekiro","strDescription":"All achievements have been unlocked.","bAchieved":true,"rtUnlocked":1617453024,"strImage":"https://cdn.steamstatic.com/steamcommunity/public/images/apps/814380/5b4b096ea3b03a5d9cb1367e53d85dd4a4300dc8.jpg","bHidden":false,"flMinProgress":0,"flCurrentProgress":0,"flMaxProgress":0,"flAchieved":9.300000190734863},{"strID":"ACH04","strName":"Height of Technique","strDescription":"Acquired all skills","bAchieved":true,"rtUnlocked":1617453024,"strImage":"https://cdn.steamstatic.com/steamcommunity/public/images/apps/814380/81b2ef0f9c0a93ca1bcfc2ef3ad67a7001daaa2a.jpg","bHidden":true,"flMinProgress":0,"flCurrentProgress":0,"flMaxProgress":0,"flAchieved":13.699999809265137},{"strID":"ACH03","strName":"Master of the Prosthetic","strDescription":"Upgraded all Prosthetic Tools to their limit","bAchieved":true,"rtUnlocked":1616959120,"strImage":"https://cdn.steamstatic.com/steamcommunity/public/images/apps/814380/183b69eaa3f8c8901a41c05959c9793f51e7d6dd.jpg","bHidden":false,"flMinProgress":0,"flCurrentProgress":0,"flMaxProgress":0,"flAchieved":13.199999809265137},{"strID":"ACH09","strName":"Immortal Severance","strDescription":"Attained the \"Immortal Severance\" ending","bAchieved":true,"rtUnlocked":1591999274,"strImage":"https://cdn.steamstatic.com/steamcommunity/public/images/apps/814380/4185b74c93880d4a7f4cb2cbf5da43a6d5fb78c2.jpg","bHidden":true,"flMinProgress":0,"flCurrentProgress":0,"flMaxProgress":0,"flAchieved":24.200000762939453},{"strID":"ACH12","strName":"Shura","strDescription":"Attained the \"Shura\" ending","bAchieved":true,"rtUnlocked":1591870555,"strImage":"https://cdn.steamstatic.com/steamcommunity/public/images/apps/814380/48258656a18fa18e31e3baa2924cdfe2fe485354.jpg","bHidden":true,"flMinProgress":0,"flCurrentProgress":0,"flMaxProgress":0,"flAchieved":18.899999618530273},{"strID":"ACH01","strName":"Man Without Equal","strDescription":"Defeated all bosses","bAchieved":true,"rtUnlocked":1591870382,"strImage":"https://cdn.steamstatic.com/steamcommunity/public/images/apps/814380/99a3f76eb4e25f821826575f361a0b8ec4de718e.jpg","bHidden":true,"flMinProgress":0,"flCurrentProgress":0,"flMaxProgress":0,"flAchieved":14.100000381469727},{"strID":"ACH30","strName":"Isshin Ashina","strDescription":"Defeated \"Isshin Ashina\"","bAchieved":true,"rtUnlocked":1591870382,"strImage":"https://cdn.steamstatic.com/steamcommunity/public/images/apps/814380/5db0731e9df3de9b5eebfe24bca954a82fdb1416.jpg","bHidden":true,"flMinProgress":0,"flCurrentProgress":0,"flMaxProgress":0,"flAchieved":19},{"strID":"ACH15","strName":"Lazuline Upgrade","strDescription":"Used Lapis Lazuli to upgrade any tool to its limit","bAchieved":true,"rtUnlocked":1586961924,"strImage":"https://cdn.steamstatic.com/steamcommunity/public/images/apps/814380/a6faa89a572614285bfa35e9417bc8afd102df27.jpg","bHidden":true,"flMinProgress":0,"flCurrentProgress":0,"flMaxProgress":0,"flAchieved":22},{"strID":"ACH10","strName":"Purification","strDescription":"Attained the \"Purification\" ending","bAchieved":true,"rtUnlocked":1585905309,"strImage":"https://cdn.steamstatic.com/steamcommunity/public/images/apps/814380/288a3e720f48d16075fb4dd5cec62cfbb20aff66.jpg","bHidden":true,"flMinProgress":0,"flCurrentProgress":0,"flMaxProgress":0,"flAchieved":16.299999237060547},{"strID":"ACH27","strName":"Father Surpassed","strDescription":"Defeated \"Great Shinobi - Owl\" at the Hirata Estate","bAchieved":true,"rtUnlocked":1584894049,"strImage":"https://cdn.steamstatic.com/steamcommunity/public/images/apps/814380/f27a15e2d29a4ed244e33c7b423dc0fbcf554ea6.jpg","bHidden":true,"flMinProgress":0,"flCurrentProgress":0,"flMaxProgress":0,"flAchieved":21.700000762939453},{"strID":"ACH07","strName":"Peak Physical Strength","strDescription":"Upgraded Vitality and Posture to their limit","bAchieved":true,"rtUnlocked":1584798057,"strImage":"https://cdn.steamstatic.com/steamcommunity/public/images/apps/814380/5789e9de2d292b9879077751ccc2a49144fdf3b3.jpg","bHidden":false,"flMinProgress":0,"flCurrentProgress":0,"flMaxProgress":0,"flAchieved":21.5},{"strID":"ACH08","strName":"Ultimate Healing Gourd","strDescription":"Fully upgraded the \"Healing Gourd\"","bAchieved":true,"rtUnlocked":1578394443,"strImage":"https://cdn.steamstatic.com/steamcommunity/public/images/apps/814380/923bc3ee8b204785cde4f5e28b659d92e62be97e.jpg","bHidden":false,"flMinProgress":0,"flCurrentProgress":0,"flMaxProgress":0,"flAchieved":27.899999618530273}],"vecUnachieved":[],"vecAchievedHidden":[{"strID":"ACH01","strName":"Man Without Equal","strDescription":"Defeated all bosses","strImage":"https://cdn.steamstatic.com/steamcommunity/public/images/apps/814380/99a3f76eb4e25f821826575f361a0b8ec4de718e.jpg","bAchieved":true,"rtUnlocked":1591870382,"flAchieved":0},{"strID":"ACH04","strName":"Height of Technique","strDescription":"Acquired all skills","strImage":"https://cdn.steamstatic.com/steamcommunity/public/images/apps/814380/81b2ef0f9c0a93ca1bcfc2ef3ad67a7001daaa2a.jpg","bAchieved":true,"rtUnlocked":1617453024,"flAchieved":0},{"strID":"ACH09","strName":"Immortal Severance","strDescription":"Attained the \"Immortal Severance\" ending","strImage":"https://cdn.steamstatic.com/steamcommunity/public/images/apps/814380/4185b74c93880d4a7f4cb2cbf5da43a6d5fb78c2.jpg","bAchieved":true,"rtUnlocked":1591999274,"flAchieved":0},{"strID":"ACH10","strName":"Purification","strDescription":"Attained the \"Purification\" ending","strImage":"https://cdn.steamstatic.com/steamcommunity/public/images/apps/814380/288a3e720f48d16075fb4dd5cec62cfbb20aff66.jpg","bAchieved":true,"rtUnlocked":1585905309,"flAchieved":0},{"strID":"ACH11","strName":"Dragon's Homecoming","strDescription":"Attained the \"Return\" ending","strImage":"https://cdn.steamstatic.com/steamcommunity/public/images/apps/814380/ad8d0504734739a55f5d06b48f9549a89a1055d7.jpg","bAchieved":true,"rtUnlocked":1578385621,"flAchieved":0},{"strID":"ACH12","strName":"Shura","strDescription":"Attained the \"Shura\" ending","strImage":"https://cdn.steamstatic.com/steamcommunity/public/images/apps/814380/48258656a18fa18e31e3baa2924cdfe2fe485354.jpg","bAchieved":true,"rtUnlocked":1591870555,"flAchieved":0},{"strID":"ACH13","strName":"Sword Saint, Isshin Ashina","strDescription":"Defeated \"Sword Saint Isshin Ashina\"","strImage":"https://cdn.steamstatic.com/steamcommunity/public/images/apps/814380/7f9f10c8cba6bad80a5ed7ad438a1fed87be9c31.jpg","bAchieved":true,"rtUnlocked":1578385405,"flAchieved":0},{"strID":"ACH14","strName":"Master of the Arts","strDescription":"Grasped the inner mysteries of any combat style","strImage":"https://cdn.steamstatic.com/steamcommunity/public/images/apps/814380/8c173e958703416e9ae3346b00f6da3ffcd49509.jpg","bAchieved":true,"rtUnlocked":1577287983,"flAchieved":0},{"strID":"ACH15","strName":"Lazuline Upgrade","strDescription":"Used Lapis Lazuli to upgrade any tool to its limit","strImage":"https://cdn.steamstatic.com/steamcommunity/public/images/apps/814380/a6faa89a572614285bfa35e9417bc8afd102df27.jpg","bAchieved":true,"rtUnlocked":1586961924,"flAchieved":0},{"strID":"ACH20","strName":"Gyoubu Masataka Oniwa","strDescription":"Defeated \"Gyoubu Masataka Oniwa\"","strImage":"https://cdn.steamstatic.com/steamcommunity/public/images/apps/814380/d43f8eeed11aa7bb34e293a0304b9be2ff566ea6.jpg","bAchieved":true,"rtUnlocked":1577010898,"flAchieved":0},{"strID":"ACH21","strName":"The Phantom Lady Butterfly","strDescription":"Defeated \"Lady Butterfly\"","strImage":"https://cdn.steamstatic.com/steamcommunity/public/images/apps/814380/f567afafa39c997eb10b29b11de0449133c04159.jpg","bAchieved":true,"rtUnlocked":1577013057,"flAchieved":0},{"strID":"ACH22","strName":"Genichiro Ashina","strDescription":"Defeated \"Genichiro Ashina\"","strImage":"https://cdn.steamstatic.com/steamcommunity/public/images/apps/814380/1705624523d452f8ca2142e7e92f5817b2ddc18f.jpg","bAchieved":true,"rtUnlocked":1577097744,"flAchieved":0},{"strID":"ACH23","strName":"Guardian Ape","strDescription":"Defeated the \"Guardian Ape\"","strImage":"https://cdn.steamstatic.com/steamcommunity/public/images/apps/814380/cbb98bfdc6c3b06d643f82debdfe7f85332c800e.jpg","bAchieved":true,"rtUnlocked":1577209330,"flAchieved":0},{"strID":"ACH24","strName":"Guardian Ape Immortality Severed","strDescription":"Used the Mortal Blade to sever the Guardian Ape's undying","strImage":"https://cdn.steamstatic.com/steamcommunity/public/images/apps/814380/01b6b0035544f52b00da5f7dedb2830b8ba4e236.jpg","bAchieved":true,"rtUnlocked":1577281203,"flAchieved":0},{"strID":"ACH25","strName":"Folding Screen Monkeys","strDescription":"Caught the Folding Screen Monkeys","strImage":"https://cdn.steamstatic.com/steamcommunity/public/images/apps/814380/25826bc23b98cd5c508186df0ffa4f366fa40d91.jpg","bAchieved":true,"rtUnlocked":1577122088,"flAchieved":0},{"strID":"ACH26","strName":"Great Shinobi - Owl","strDescription":"Defeated \"Great Shinobi - Owl\"","strImage":"https://cdn.steamstatic.com/steamcommunity/public/images/apps/814380/5193764fa7fc7e1cae6efd0188235aecf645714e.jpg","bAchieved":true,"rtUnlocked":1577300421,"flAchieved":0},{"strID":"ACH27","strName":"Father Surpassed","strDescription":"Defeated \"Great Shinobi - Owl\" at the Hirata Estate","strImage":"https://cdn.steamstatic.com/steamcommunity/public/images/apps/814380/f27a15e2d29a4ed244e33c7b423dc0fbcf554ea6.jpg","bAchieved":true,"rtUnlocked":1584894049,"flAchieved":0},{"strID":"ACH28","strName":"Corrupted Monk","strDescription":"Defeated the \"Corrupted Monk\"","strImage":"https://cdn.steamstatic.com/steamcommunity/public/images/apps/814380/d458b5fd1f5008946abfdf648ad446bedc5e5c25.jpg","bAchieved":true,"rtUnlocked":1577374121,"flAchieved":0},{"strID":"ACH29","strName":"Gracious Gift of Tears","strDescription":"Defeated the \"Divine Dragon\" and obtained the \"Divine Dragon's Tears\"","strImage":"https://cdn.steamstatic.com/steamcommunity/public/images/apps/814380/ed01dca1fb4a7679debb6fc46ca2758e9167e3f0.jpg","bAchieved":true,"rtUnlocked":1577437857,"flAchieved":0},{"strID":"ACH30","strName":"Isshin Ashina","strDescription":"Defeated \"Isshin Ashina\"","strImage":"https://cdn.steamstatic.com/steamcommunity/public/images/apps/814380/5db0731e9df3de9b5eebfe24bca954a82fdb1416.jpg","bAchieved":true,"rtUnlocked":1591870382,"flAchieved":0},{"strID":"ACH31","strName":"Demon of Hatred","strDescription":"Defeated the \"Demon of Hatred\"","strImage":"https://cdn.steamstatic.com/steamcommunity/public/images/apps/814380/11baf3a1dcacb21bc8fe13f1ef2680fb517294ba.jpg","bAchieved":true,"rtUnlocked":1578394304,"flAchieved":0},{"strID":"ACH32","strName":"Great Serpent","strDescription":"Defeated the \"Great Serpent\".","strImage":"https://cdn.steamstatic.com/steamcommunity/public/images/apps/814380/eb13395291644f15a725ee88fac202c0dc06ff37.jpg","bAchieved":true,"rtUnlocked":1577211252,"flAchieved":0},{"strID":"ACH33","strName":"Great Colored Carp","strDescription":"Defeated the \"Great Colored Carp\".","strImage":"https://cdn.steamstatic.com/steamcommunity/public/images/apps/814380/2de71a2408d54a007edc335cfcac2f5e5ee9bb46.jpg","bAchieved":true,"rtUnlocked":1578387490,"flAchieved":0}],"nTotal":34,"nAchieved":34}}],["badge",{"version":1,"data":{"dtNextRetry":null,"strName":"","strIconURL":"https://cdn.akamai.steamstatic.com/steamcommunity/public/images/items/814380/","nLevel":0,"nMaxLevel":5,"nXP":0,"bMaxed":null,"strNextLevelName":"Empty Healing Gourd","nNextLevelXP":100,"rgCards":[{"strName":"Kuro","strTitle":"Kuro","strImgURL":"https://community.akamai.steamstatic.com/economy/image/IzMF03bk9WpSBq-S-ekoE33L-iLqGFHVaU25ZzQNQcXdA3g5gMEPvUZZEfSMJ6dESN8p_2SVTY7V2NEOwHAEmChCIzb02ClGcPdjfsLLwQL-_OSLTiLzP2KQLHOPGQ1pGOFWN2rc-TH3tL6SEz6fEL0oQQFVdPMNoTZXfZfeKUBiltNeuVqxmkV6G0t4J8QTdA6_kiZAYuUhzSIXd5oHmnalcpXf0Q42YBI-C7-2ArTHPtCljm96CgwhEqJCzLYnQg","strArtworkURL":"https://cdn.akamai.steamstatic.com/steamcommunity/public/images/items/814380/8b6a4b687b12845f0dcb82596911b274b0d56ba1.jpg","strMarketHash":"814380-Kuro","nOwned":0},{"strName":"Sculptor","strTitle":"Sculptor","strImgURL":"https://community.akamai.steamstatic.com/economy/image/IzMF03bk9WpSBq-S-ekoE33L-iLqGFHVaU25ZzQNQcXdA3g5gMEPvUZZEfSMJ6dESN8p_2SVTY7V2NEOwHAEmChCIzb02CleZvBgKN_J0kPyrOOKGSmmOWGSfnndSF9uS7VaY2_a-zTw5uqWRDuYQO9-RA8Ce_MAoTVKbpyAIVJjg5FZpHe8klZCFxspdcAbIFq6n3ASNeV3m3JKIc4BzCbxc5eL0AtjbhI7DrCzAu3FPtWtlX51XQQnQfcMIoaXuCat20I","strArtworkURL":"https://cdn.akamai.steamstatic.com/steamcommunity/public/images/items/814380/feb206f717e94bfce096c63c75524793f7b84c25.jpg","strMarketHash":"814380-Sculptor","nOwned":0},{"strName":"Emma","strTitle":"Emma","strImgURL":"https://community.akamai.steamstatic.com/economy/image/IzMF03bk9WpSBq-S-ekoE33L-iLqGFHVaU25ZzQNQcXdA3g5gMEPvUZZEfSMJ6dESN8p_2SVTY7V2NEOwHAEmChCIzb02ClIaOhtfsLLwQL-_LGORHajbWWdfiSMTlw7S7RaMz6M9mfx4-iRQzqbFOwtFVxQeapV9TVXfZfeKUBiltNeuVqxmkV6G0t4J8QTdA6_kiZAYuUhzSIXd5oHmnalcpXf0Q42YBI-C7-2ArTHPtCljm96CgwhEqLwEWFfcQ","strArtworkURL":"https://cdn.akamai.steamstatic.com/steamcommunity/public/images/items/814380/72bf9b6aeb54d26557db01feb33931546c87bd42.jpg","strMarketHash":"814380-Emma","nOwned":0},{"strName":"Genichiro Ashina","strTitle":"Genichiro Ashina","strImgURL":"https://community.akamai.steamstatic.com/economy/image/IzMF03bk9WpSBq-S-ekoE33L-iLqGFHVaU25ZzQNQcXdA3g5gMEPvUZZEfSMJ6dESN8p_2SVTY7V2NEOwHAEmChCIzb02ClKYOtlO8PP0gqwgPGFFXr2Lj7JLibcQV8_TbdYNm6M_zP05-3HF27MQOF6QgACK6cBo2IaPs6ObBI10oIM-jX2h0p6WBQnYMFDYjCyx3UUNOB1nSBHIcoGkSbzJZyN0Aw3akc_WeqyAr3EO9DxmHtwDB02S6gfNdqVpmWyr4G3Z_US1Yi_hw","strArtworkURL":"https://cdn.akamai.steamstatic.com/steamcommunity/public/images/items/814380/06ec39d830002c0b003a190477897b556df405ba.jpg","strMarketHash":"814380-Genichiro Ashina","nOwned":0},{"strName":"Owl","strTitle":"Owl","strImgURL":"https://community.akamai.steamstatic.com/economy/image/IzMF03bk9WpSBq-S-ekoE33L-iLqGFHVaU25ZzQNQcXdA3g5gMEPvUZZEfSMJ6dESN8p_2SVTY7V2NEOwHAEmChCIzb02ClCcukqMcbHxwCm9bPZGCygbDSTfSfbSgxqHuBbYD7ZqDug4b6SETmcEO8pQVsNKaYEo3oJY56fbU1_gNJJlGy1lkN4Q0Z9c5BCcQvjmCdAabkgyyRAdM5Ry3GkJ5KN1AtqPBI7XemzXrmTPoG70HFzS1xqHeMRsXPD","strArtworkURL":"https://cdn.akamai.steamstatic.com/steamcommunity/public/images/items/814380/056b632957d07be8e9b6f809e6538c3b9219afa6.jpg","strMarketHash":"814380-Owl","nOwned":0},{"strName":"Corrupted Monk","strTitle":"Corrupted Monk","strImgURL":"https://community.akamai.steamstatic.com/economy/image/IzMF03bk9WpSBq-S-ekoE33L-iLqGFHVaU25ZzQNQcXdA3g5gMEPvUZZEfSMJ6dESN8p_2SVTY7V2NEOwHAEmChCIzb02ClOavd-LdvSxQGwjO2DFzL-ZTbDKnzaHQ04S-UKNmHdqjDz5--VSmnLQex5QgEAKaVV9DFIOZ-AbhE9hodd5XW2kAJ_EQQsd9d5eQK6zXFOYegknSUTIZNQmif4csGK0F1jPUU4D-zmUOiTO4nxxH4jDE5vGvFLZJXV5nL6vprzOW7ZRHE","strArtworkURL":"https://cdn.akamai.steamstatic.com/steamcommunity/public/images/items/814380/abf137d637c03aed40c4e5efca026341365eb1b4.jpg","strMarketHash":"814380-Corrupted Monk","nOwned":0},{"strName":"Gyoubu Oniwa","strTitle":"Gyoubu Oniwa","strImgURL":"https://community.akamai.steamstatic.com/economy/image/IzMF03bk9WpSBq-S-ekoE33L-iLqGFHVaU25ZzQNQcXdA3g5gMEPvUZZEfSMJ6dESN8p_2SVTY7V2NEOwHAEmChCIzb02ClKfOp5Ot6N7wvytuPLFXn2bzKZeiXaSg04HrZaY2CI-zCktOjCFj_LE7woEAwNe_MD8DIYaMCKbkY61JlLpWL-lUtvGhM6TcxLcQi-lyRGMOghySVKd5hRkXCldcHbhAphOhM-W76zB-jKO9X0l35wVR82TqAEJNXCrmPh-j7eT0vv","strArtworkURL":"https://cdn.akamai.steamstatic.com/steamcommunity/public/images/items/814380/5d0f4a4f95c94fde8c566dd5fe074f6adf5b431e.jpg","strMarketHash":"814380-Gyoubu Oniwa","nOwned":0},{"strName":"General Tenzen Yamauchi","strTitle":"General Tenzen Yamauchi","strImgURL":"https://community.akamai.steamstatic.com/economy/image/IzMF03bk9WpSBq-S-ekoE33L-iLqGFHVaU25ZzQNQcXdA3g5gMEPvUZZEfSMJ6dESN8p_2SVTY7V2NEOwHAEmChCIzb02ClKYOtpKsrKizH-r_iIEj_OaTrFOiLRFRhhEOIJYGXd9jL37LvCS2yYROktQggNK6AA9WJBPs7cPhA61IYJ_TbqxRF-ThB9PNVId0m5xWYXNK8awSwTIs5fmSGhI8CI0Vdga0ViDu20A77DOoL3xXslW042S6hOMNqS6XHk_cagaunGc68hIvw130XIJfs","strArtworkURL":"https://cdn.akamai.steamstatic.com/steamcommunity/public/images/items/814380/237bb0ec2517f54ee0ea2296816e6e7534d5d89e.jpg","strMarketHash":"814380-General Tenzen Yamauchi","nOwned":0},{"strName":"Dilapidated Temple","strTitle":"Dilapidated Temple","strImgURL":"https://community.akamai.steamstatic.com/economy/image/IzMF03bk9WpSBq-S-ekoE33L-iLqGFHVaU25ZzQNQcXdA3g5gMEPvUZZEfSMJ6dESN8p_2SVTY7V2NEOwHAEmChCIzb02ClJbOltKMLCwRH-pam5GXnnZDKCJizYG1s1G-VfZmuN9mH25r-SSjqfQep5EAhVfqZWpG0absyLPRFo1NEP-2fplgptEBFucMpUdAqp9X0eMLoglXFHJJ4GyHD4JJfajQs3OxNoW-3kBOmWbofxwXssCU42GPFObI7E6SXyuMmmfLGLLwCk8VAb","strArtworkURL":"https://cdn.akamai.steamstatic.com/steamcommunity/public/images/items/814380/66d957bbe9271a3060016ee0377b7aee44f58d79.jpg","strMarketHash":"814380-Dilapidated Temple","nOwned":0},{"strName":"Kuro's Room","strTitle":"Kuro's Room","strImgURL":"https://community.akamai.steamstatic.com/economy/image/IzMF03bk9WpSBq-S-ekoE33L-iLqGFHVaU25ZzQNQcXdA3g5gMEPvUZZEfSMJ6dESN8p_2SVTY7V2NEOwHAEmChCIzb02ClGcPdjfZmR007Jru2AWn36aTDBcnePGF86T-YPMGzY_zbzsevGQW2YF-B_FVwEevQCoDZLPsGAbBZvhYcVu2u_0UZyDBItYPpPfQ68zylDZLxwzCAWfZlRmiykc8eMh143axQ_DrnhAu2WZ9XxwSh1CRJiTvEaesvL7zOq9ZWvZ6R48A","strArtworkURL":"https://cdn.akamai.steamstatic.com/steamcommunity/public/images/items/814380/9973bb2803ac0ae1c66f97455bd914457ae3f519.jpg","strMarketHash":"814380-Kuro's Room","nOwned":0},{"strName":"Hidden Temple","strTitle":"Hidden Temple","strImgURL":"https://community.akamai.steamstatic.com/economy/image/IzMF03bk9WpSBq-S-ekoE33L-iLqGFHVaU25ZzQNQcXdA3g5gMEPvUZZEfSMJ6dESN8p_2SVTY7V2NEOwHAEmChCIzb02ClFbOFoPcWN9AD2se6IWn36aTDBciSKGQxtGbNaZGyLqjCm7LvBFDrPSOB5QwgMKKZSpDZOO8GLaxA1gdIVu2u_0UZyDBItYPpPfQ68zylDZLxwzCAWfZlRmiykc8eMh143axQ_DrnhAu2WZ9XxwSh1CRJiTvEaesvL7zOq9ZXjAbPqzg","strArtworkURL":"https://cdn.akamai.steamstatic.com/steamcommunity/public/images/items/814380/1f80a15816540d15cc4cfcbf8d500aa323b7a76f.jpg","strMarketHash":"814380-Hidden Temple","nOwned":0},{"strName":"Fountainhead Palace","strTitle":"Fountainhead Palace","strImgURL":"https://community.akamai.steamstatic.com/economy/image/IzMF03bk9WpSBq-S-ekoE33L-iLqGFHVaU25ZzQNQcXdA3g5gMEPvUZZEfSMJ6dESN8p_2SVTY7V2NEOwHAEmChCIzb02ClLavBiLMrPzg3-oObGLHX7aTTBaSjUHVltQOBfZDzd-mHz4-SUQz_OSLkpS1sFe6cHoWwba5rcPhs41Y4I8jDrwxMzDhgvNMdJYgu-2EsaPLwizXxCcMpXzXWkLpbahlc2PRU_WLmyVe6XO4CjxH5wVU4zTqdLMIOQ6XTs5tevPeHAIPp4H7i0tQ","strArtworkURL":"https://cdn.akamai.steamstatic.com/steamcommunity/public/images/items/814380/3f83bdd2aee00d7f900a0187fc22dab7d5ae9b06.jpg","strMarketHash":"814380-Fountainhead Palace","nOwned":0}]}}],["socialmedia",{"version":3,"data":[]}],["associations",{"version":2,"data":{"rgDevelopers":[{"strName":"FromSoftware","strURL":null}],"rgPublishers":[{"strName":"Activision (Excluding Japan and Asia)","strURL":"https://store.steampowered.com/publisher/CubeGame"},{"strName":"FromSoftware (Japan)","strURL":null},{"strName":"方块游戏 (Asia)","strURL":"https://store.steampowered.com/publisher/CubeGame"}],"rgFranchises":[]}}],["descriptions",{"version":1,"data":{"strFullDescription":"This Game of the Year Edition now includes bonus content*:\r\n\r\n- Reflection and Gauntlet of Strength - new boss challenge modes\r\n- Remnants - leave messages and recordings of your actions that other players can view and rate\r\n- 3 unlockable cosmetic skins\r\n\r\nGame of the Year  - The Game Awards 2019\r\nBest Action Game of 2019 - IGN\r\nOver 50 awards and nominations\r\n\r\nCarve your own clever path to vengeance in the critically acclaimed adventure from developer FromSoftware, creators of the Dark Souls series.\r\n\r\nIn Sekiro™: Shadows Die Twice you are the 'one-armed wolf', a disgraced and disfigured warrior rescued from the brink of death. Bound to protect a young lord who is the descendant of an ancient bloodline, you become the target of many vicious enemies, including the dangerous Ashina clan. When the young lord is captured, nothing will stop you on a perilous quest to regain your honor, not even death itself.\r\n\r\nExplore late 1500s Sengoku Japan, a brutal period of constant life and death conflict, as you come face to face with larger than life foes in a dark and twisted world. Unleash an arsenal of deadly prosthetic tools and powerful ninja abilities while you blend stealth, vertical traversal, and visceral head to head combat in a bloody confrontation.\r\n\r\nTake Revenge. Restore Your Honor. Kill Ingeniously.\r\n\r\n*Download required.\r\n\r\nInternet connection required for asynchronous Multiplayer.","strSnippet":"Game of the Year - The Game Awards 2019 Best Action Game of 2019 - IGN Carve your own clever path to vengeance in the award winning adventure from developer FromSoftware, creators of Bloodborne and the Dark Souls series. Take Revenge. Restore Your Honor. Kill Ingeniously."}}],["achievementmap",{"version":5,"data":"[[814380,[[\"ACH22\",{\"strName\":\"Genichiro Ashina\",\"strDescription\":\"Defeated \\\"Genichiro Ashina\\\"\",\"strImage\":\"https://cdn.steamstatic.com/steamcommunity/public/images/apps/814380/1705624523d452f8ca2142e7e92f5817b2ddc18f.jpg\",\"bAchieved\":true,\"flAchieved\":46.599998474121094,\"bHidden\":true,\"strID\":\"ACH22\",\"rtUnlocked\":0}],[\"ACH23\",{\"strName\":\"Guardian Ape\",\"strDescription\":\"Defeated the \\\"Guardian Ape\\\"\",\"strImage\":\"https://cdn.steamstatic.com/steamcommunity/public/images/apps/814380/cbb98bfdc6c3b06d643f82debdfe7f85332c800e.jpg\",\"bAchieved\":true,\"flAchieved\":41.20000076293945,\"bHidden\":true,\"strID\":\"ACH23\",\"rtUnlocked\":0}],[\"ACH25\",{\"strName\":\"Folding Screen Monkeys\",\"strDescription\":\"Caught the Folding Screen Monkeys\",\"strImage\":\"https://cdn.steamstatic.com/steamcommunity/public/images/apps/814380/25826bc23b98cd5c508186df0ffa4f366fa40d91.jpg\",\"bAchieved\":true,\"flAchieved\":43,\"bHidden\":true,\"strID\":\"ACH25\",\"rtUnlocked\":0}],[\"ACH14\",{\"strName\":\"Master of the Arts\",\"strDescription\":\"Grasped the inner mysteries of any combat style\",\"strImage\":\"https://cdn.steamstatic.com/steamcommunity/public/images/apps/814380/8c173e958703416e9ae3346b00f6da3ffcd49509.jpg\",\"bAchieved\":true,\"flAchieved\":40.599998474121094,\"bHidden\":true,\"strID\":\"ACH14\",\"rtUnlocked\":0}],[\"ACH21\",{\"strName\":\"The Phantom Lady Butterfly\",\"strDescription\":\"Defeated \\\"Lady Butterfly\\\"\",\"strImage\":\"https://cdn.steamstatic.com/steamcommunity/public/images/apps/814380/f567afafa39c997eb10b29b11de0449133c04159.jpg\",\"bAchieved\":true,\"flAchieved\":48.70000076293945,\"bHidden\":true,\"strID\":\"ACH21\",\"rtUnlocked\":0}]]]]"}],["usernews",{"version":5,"data":["CA0Qh7u9rwYZm4ceSgEAEAEpLG0MAAAAAABZDPWCvQAAAAA=","CA0Qgru9rwYZm4ceSgEAEAEpLG0MAAAAAABZrPSCvQAAAAA=","CAIQ2Za8rwYZm4ceSgEAEAEhAAAAAAAAAAApLG0MAAAAAABCBUFDSDIyQgVBQ0gyM0IFQUNIMjU=","CA0Q/by3rwYZm4ceSgEAEAEpLG0MAAAAAABZkQlrvQAAAAA=","CAIQu521rwYZm4ceSgEAEAEhAAAAAAAAAAApLG0MAAAAAABCBUFDSDE0QgVBQ0gyMQ==","CA0QktmwrwYZm4ceSgEAEAEpLG0MAAAAAABZe5dOvQAAAAA=","CA0Qh9mwrwYZm4ceSgEAEAEpLG0MAAAAAABZ3pZOvQAAAAA="]}],["gameactivity",{"version":5,"data":[]}]]