[["achievements",{"version":2,"data":{"vecHighlight":[{"strID":"BIOME_SNOWCASTLE","strName":"Reached Hiisi Base","strDescription":"Reached Hiisi Base","bAchieved":true,"rtUnlocked":1722103694,"strImage":"https://cdn.steamstatic.com/steamcommunity/public/images/apps/881100/c219c3651fcf6dd48c3db6fbbbbd18a39c397697.jpg","bHidden":true,"flMinProgress":0,"flCurrentProgress":0,"flMaxProgress":0,"flAchieved":36.70000076293945},{"strID":"BIOME_SNOWCAVE","strName":"Reached Snowy Depths","strDescription":"Reached Snowy Depths","bAchieved":true,"rtUnlocked":1721667085,"strImage":"https://cdn.steamstatic.com/steamcommunity/public/images/apps/881100/84d2845edbfe01a27b855f235023d7ea5f3e770a.jpg","bHidden":true,"flMinProgress":0,"flCurrentProgress":0,"flMaxProgress":0,"flAchieved":58.5},{"strID":"BIOME_EXCAVATION_SITE","strName":"Reached Coal Pits","strDescription":"Reached Coal Pits","bAchieved":true,"rtUnlocked":1721666823,"strImage":"https://cdn.steamstatic.com/steamcommunity/public/images/apps/881100/758f9b900906a4dd07fc120aba01daf5e3851045.jpg","bHidden":true,"flMinProgress":0,"flCurrentProgress":0,"flMaxProgress":0,"flAchieved":71.4000015258789}],"vecUnachieved":[{"strID":"BEAT_THE_GAME","strName":"Victory","strDescription":"Victory","strImage":"https://cdn.steamstatic.com/steamcommunity/public/images/apps/881100/9da1275f4eda0d051d2b0beef3f7aa8d6ed24297.jpg","bAchieved":false,"rtUnlocked":0,"flAchieved":9.800000190734863,"flMinProgress":0,"flCurrentProgress":0,"flMaxProgress":0}],"vecAchievedHidden":[{"strID":"BIOME_EXCAVATION_SITE","strName":"Reached Coal Pits","strDescription":"Reached Coal Pits","strImage":"https://cdn.steamstatic.com/steamcommunity/public/images/apps/881100/758f9b900906a4dd07fc120aba01daf5e3851045.jpg","bAchieved":true,"rtUnlocked":1721666823,"flAchieved":0},{"strID":"BIOME_SNOWCASTLE","strName":"Reached Hiisi Base","strDescription":"Reached Hiisi Base","strImage":"https://cdn.steamstatic.com/steamcommunity/public/images/apps/881100/c219c3651fcf6dd48c3db6fbbbbd18a39c397697.jpg","bAchieved":true,"rtUnlocked":1722103694,"flAchieved":0},{"strID":"BIOME_SNOWCAVE","strName":"Reached Snowy Depths","strDescription":"Reached Snowy Depths","strImage":"https://cdn.steamstatic.com/steamcommunity/public/images/apps/881100/84d2845edbfe01a27b855f235023d7ea5f3e770a.jpg","bAchieved":true,"rtUnlocked":1721667085,"flAchieved":0}],"nTotal":14,"nAchieved":3}}]]