[["achievements",{"version":2,"data":{"vecHighlight":[{"strID":"Achievement_ALL_UNLOCK","strName":"Super-Perfectionst","strDescription":"Mastered Chaos;Child","bAchieved":true,"rtUnlocked":1568358623,"strImage":"https://cdn.steamstatic.com/steamcommunity/public/images/apps/970570/a10200e848a433997f684d338172b107b1bb0ec2.jpg","bHidden":false,"flMinProgress":0,"flCurrentProgress":0,"flMaxProgress":0,"flAchieved":9.699999809265137},{"strID":"Achievement_READ_ALL_TIPS","strName":"TIPS Complete","strDescription":"Saw All TIPS","bAchieved":true,"rtUnlocked":1568358623,"strImage":"https://cdn.steamstatic.com/steamcommunity/public/images/apps/970570/96429a0368dc5cf21c3f6ab1b9b233cd26c291f7.jpg","bHidden":false,"flMinProgress":0,"flCurrentProgress":0,"flMaxProgress":0,"flAchieved":12.800000190734863},{"strID":"Achievement_LISTEN_ALL_SOUND","strName":"Sound Complete","strDescription":"Listened to All Sound","bAchieved":true,"rtUnlocked":1568349896,"strImage":"https://cdn.steamstatic.com/steamcommunity/public/images/apps/970570/501aa88992c947084b4df4717b240777afd2a999.jpg","bHidden":false,"flMinProgress":0,"flCurrentProgress":0,"flMaxProgress":0,"flAchieved":25},{"strID":"Achievement_PASS_TRUE","strName":"Chaos Child","strDescription":"Reached the Silent Sky End","bAchieved":true,"rtUnlocked":1568349892,"strImage":"https://cdn.steamstatic.com/steamcommunity/public/images/apps/970570/87256df061f1d98b3fce5c9aba36d29bb39ad39c.jpg","bHidden":true,"flMinProgress":0,"flCurrentProgress":0,"flMaxProgress":0,"flAchieved":24.700000762939453},{"strID":"Achievement_OPEN_ALL_EV","strName":"CG Complete","strDescription":"Saw All Event CG","bAchieved":true,"rtUnlocked":1568349661,"strImage":"https://cdn.steamstatic.com/steamcommunity/public/images/apps/970570/84e4cade43e288c9b993e6af46ab72148e13059c.jpg","bHidden":false,"flMinProgress":0,"flCurrentProgress":0,"flMaxProgress":0,"flAchieved":14.300000190734863},{"strID":"Achievement_COMPLETE_STUCK_DOC","strName":"I Am a Right-Sider","strDescription":"Made No Mistakes When Putting Up The Data","bAchieved":true,"rtUnlocked":1568038406,"strImage":"https://cdn.steamstatic.com/steamcommunity/public/images/apps/970570/fa6daa8090a9ee58174c65988b91f53d5856affe.jpg","bHidden":false,"flMinProgress":0,"flCurrentProgress":0,"flMaxProgress":0,"flAchieved":13.300000190734863},{"strID":"Achievement_ALL_TRIGGER","strName":"Gigalomaniac","strDescription":"Tried All Delusion Triggers","bAchieved":true,"rtUnlocked":1567960502,"strImage":"https://cdn.steamstatic.com/steamcommunity/public/images/apps/970570/8b71d7a8f648e5b78b59092269ef6d062d582b22.jpg","bHidden":false,"flMinProgress":0,"flCurrentProgress":0,"flMaxProgress":0,"flAchieved":12.399999618530273},{"strID":"Achievement_ALL_NEGATIVE","strName":"A Negative Person (Third Time)","strDescription":"Saw All Negative Delusions","bAchieved":true,"rtUnlocked":1567960501,"strImage":"https://cdn.steamstatic.com/steamcommunity/public/images/apps/970570/d4d87ded0540ae9b3c59082513e0f5fd831f555e.jpg","bHidden":false,"flMinProgress":0,"flCurrentProgress":0,"flMaxProgress":0,"flAchieved":13.699999809265137},{"strID":"Achievement_PASS_NONO","strName":"Heads or Tails","strDescription":"Reached the Real Sky End","bAchieved":true,"rtUnlocked":1567960470,"strImage":"https://cdn.steamstatic.com/steamcommunity/public/images/apps/970570/2402b799175ef5a38e8b5dd2c926a105f4fd2c08.jpg","bHidden":true,"flMinProgress":0,"flCurrentProgress":0,"flMaxProgress":0,"flAchieved":25.299999237060547},{"strID":"Achievement_FOUND_THE_TRUE","strName":"Okay","strDescription":"Discovered the True Route","bAchieved":true,"rtUnlocked":1567960469,"strImage":"https://cdn.steamstatic.com/steamcommunity/public/images/apps/970570/690d7ef0d2643ed0f49ec9655ffbc226d13efbce.jpg","bHidden":true,"flMinProgress":0,"flCurrentProgress":0,"flMaxProgress":0,"flAchieved":25},{"strID":"Achievement_ALL_POSITIVE","strName":"A Positive Person (Third Time)","strDescription":"Saw All Positive Delusions","bAchieved":true,"rtUnlocked":1567942115,"strImage":"https://cdn.steamstatic.com/steamcommunity/public/images/apps/970570/564bf338593c5d178d69073a41dfd2786fd23191.jpg","bHidden":false,"flMinProgress":0,"flCurrentProgress":0,"flMaxProgress":0,"flAchieved":20.600000381469727},{"strID":"Achievement_20_MISS_MAP","strName":"I Knew You Were a Wrong-Sider","strDescription":"Got It Wrong On a Mapping Trigger 20 Times","bAchieved":true,"rtUnlocked":1567854991,"strImage":"https://cdn.steamstatic.com/steamcommunity/public/images/apps/970570/313f75c412f8ece3d4cffa30c7f31ef0171f5261.jpg","bHidden":false,"flMinProgress":0,"flCurrentProgress":0,"flMaxProgress":0,"flAchieved":16.700000762939453}],"vecUnachieved":[],"vecAchievedHidden":[{"strID":"Achievement_FOUND_THE_HANA","strName":"Mmm!","strDescription":"Discovered Hana Kazuki’s Chapter","strImage":"https://cdn.steamstatic.com/steamcommunity/public/images/apps/970570/e7898ac47eb2f60c2a1af1d6a14d28ac561d9b12.jpg","bAchieved":true,"rtUnlocked":1567093414,"flAchieved":0},{"strID":"Achievement_FOUND_THE_HINAE","strName":"Adios Gracias!","strDescription":"Discovered Hinae Arimura’s Chapter","strImage":"https://cdn.steamstatic.com/steamcommunity/public/images/apps/970570/dfdc184df5db9835bacf4521c27fecd7a32dcc95.jpg","bAchieved":true,"rtUnlocked":1566816057,"flAchieved":0},{"strID":"Achievement_FOUND_THE_NONO","strName":"Give Up on the Case, Takuru","strDescription":"Discovered Nono Kurusu’s Chapter","strImage":"https://cdn.steamstatic.com/steamcommunity/public/images/apps/970570/3a30defc6860f490afef4481c310a7894776e54e.jpg","bAchieved":true,"rtUnlocked":1567853411,"flAchieved":0},{"strID":"Achievement_FOUND_THE_TRUE","strName":"Okay","strDescription":"Discovered the True Route","strImage":"https://cdn.steamstatic.com/steamcommunity/public/images/apps/970570/690d7ef0d2643ed0f49ec9655ffbc226d13efbce.jpg","bAchieved":true,"rtUnlocked":1567960469,"flAchieved":0},{"strID":"Achievement_FOUND_THE_UKI","strName":"U-Umm…","strDescription":"Discovered Uki Yamazoe’s Chapter","strImage":"https://cdn.steamstatic.com/steamcommunity/public/images/apps/970570/ea7b8a2ada1456930c83667740ec10d7abde4f50.jpg","bAchieved":true,"rtUnlocked":1567523742,"flAchieved":0},{"strID":"Achievement_PASS_CHAPTER_11","strName":"First Ending","strDescription":"Reached the Over Sky End","strImage":"https://cdn.steamstatic.com/steamcommunity/public/images/apps/970570/fe04c4bff29123d63f950d0cabb06763acc413e0.jpg","bAchieved":true,"rtUnlocked":1566682554,"flAchieved":0},{"strID":"Achievement_PASS_HANA","strName":"Pandemic Call","strDescription":"Reached the Deep Sky End","strImage":"https://cdn.steamstatic.com/steamcommunity/public/images/apps/970570/f6eb88cd4a39843bf2fb573912c9e7b4fd9cd2c6.jpg","bAchieved":true,"rtUnlocked":1567437224,"flAchieved":0},{"strID":"Achievement_PASS_HINAE","strName":"True World","strDescription":"Reached the Dark Sky End","strImage":"https://cdn.steamstatic.com/steamcommunity/public/images/apps/970570/3806d8b585e9841d5f9d54f7a7916d9242d2c133.jpg","bAchieved":true,"rtUnlocked":1566899518,"flAchieved":0},{"strID":"Achievement_PASS_NONO","strName":"Heads or Tails","strDescription":"Reached the Real Sky End","strImage":"https://cdn.steamstatic.com/steamcommunity/public/images/apps/970570/2402b799175ef5a38e8b5dd2c926a105f4fd2c08.jpg","bAchieved":true,"rtUnlocked":1567960470,"flAchieved":0},{"strID":"Achievement_PASS_TRUE","strName":"Chaos Child","strDescription":"Reached the Silent Sky End","strImage":"https://cdn.steamstatic.com/steamcommunity/public/images/apps/970570/87256df061f1d98b3fce5c9aba36d29bb39ad39c.jpg","bAchieved":true,"rtUnlocked":1568349892,"flAchieved":0},{"strID":"Achievement_PASS_UKI","strName":"Butterfly","strDescription":"Reached the Dream Sky End","strImage":"https://cdn.steamstatic.com/steamcommunity/public/images/apps/970570/5058d087a9dbdd0043e3d02c449dd46bc9aef3bb.jpg","bAchieved":true,"rtUnlocked":1567786103,"flAchieved":0},{"strID":"Achievement_START_CHAPTER_1","strName":"Digital Native","strDescription":"Started Chapter 1","strImage":"https://cdn.steamstatic.com/steamcommunity/public/images/apps/970570/4f0e1e30442060aa564430d0526aa5526daf837a.jpg","bAchieved":true,"rtUnlocked":1563006194,"flAchieved":0},{"strID":"Achievement_START_CHAPTER_10","strName":"Serika Onoe","strDescription":"Started Chapter 10","strImage":"https://cdn.steamstatic.com/steamcommunity/public/images/apps/970570/049ce49e88b406ac06f693a1c6cffbecc020a2f9.jpg","bAchieved":true,"rtUnlocked":1566298485,"flAchieved":0},{"strID":"Achievement_START_CHAPTER_11","strName":"Takuru Miyashiro","strDescription":"Started Chapter 11","strImage":"https://cdn.steamstatic.com/steamcommunity/public/images/apps/970570/2b0144481ffd35ee7b0c5a9ffb9c115bc30febe0.jpg","bAchieved":true,"rtUnlocked":1566460047,"flAchieved":0},{"strID":"Achievement_START_CHAPTER_2","strName":"Sumo Sticker","strDescription":"Started Chapter 2","strImage":"https://cdn.steamstatic.com/steamcommunity/public/images/apps/970570/e989e127e3e8423b8916bc82fd5b02b74f9ac1e7.jpg","bAchieved":true,"rtUnlocked":1564263216,"flAchieved":0},{"strID":"Achievement_START_CHAPTER_3","strName":"School Festival!","strDescription":"Started Chapter 3","strImage":"https://cdn.steamstatic.com/steamcommunity/public/images/apps/970570/606cfdf24e13653c2e9c3f38f6ce6035c930dcff.jpg","bAchieved":true,"rtUnlocked":1564648489,"flAchieved":0},{"strID":"Achievement_START_CHAPTER_4","strName":"Her Words","strDescription":"Started Chapter 4","strImage":"https://cdn.steamstatic.com/steamcommunity/public/images/apps/970570/853a516983405c34ea996750a80eb638cf16962c.jpg","bAchieved":true,"rtUnlocked":1565087427,"flAchieved":0},{"strID":"Achievement_START_CHAPTER_5","strName":"Gigalomaniacs","strDescription":"Started Chapter 5","strImage":"https://cdn.steamstatic.com/steamcommunity/public/images/apps/970570/ee4fe9fd85fdb040dae70057725bf2f233d0c49b.jpg","bAchieved":true,"rtUnlocked":1565467066,"flAchieved":0},{"strID":"Achievement_START_CHAPTER_6","strName":"Their Resistance I","strDescription":"Started Chapter 6","strImage":"https://cdn.steamstatic.com/steamcommunity/public/images/apps/970570/ec2d4b692bfb0cc33d45d548623323c9817ecf62.jpg","bAchieved":true,"rtUnlocked":1565686812,"flAchieved":0},{"strID":"Achievement_START_CHAPTER_7","strName":"Their Resistance II","strDescription":"Started Chapter 7","strImage":"https://cdn.steamstatic.com/steamcommunity/public/images/apps/970570/fea95e74bbd671e8470737aa256a64c8eeeae6b1.jpg","bAchieved":true,"rtUnlocked":1565789904,"flAchieved":0},{"strID":"Achievement_START_CHAPTER_8","strName":"Betrayal","strDescription":"Started Chapter 8","strImage":"https://cdn.steamstatic.com/steamcommunity/public/images/apps/970570/e0b47bb179e22a9a8cb9d04ce64c1d16d38e81e7.jpg","bAchieved":true,"rtUnlocked":1566039479,"flAchieved":0},{"strID":"Achievement_START_CHAPTER_9","strName":"Duel","strDescription":"Started Chapter 9","strImage":"https://cdn.steamstatic.com/steamcommunity/public/images/apps/970570/e7f4846d64f8d2b99a55509a75c297fd069f0173.jpg","bAchieved":true,"rtUnlocked":1566157217,"flAchieved":0}],"nTotal":34,"nAchieved":34}}],["badge",{"version":1,"data":{"dtNextRetry":null,"strName":"Mountain View","strIconURL":"https://cdn.akamai.steamstatic.com/steamcommunity/public/images/items/970570/98a660d787eefcf8853c1bb0efcd318ee8bd3418.png","nLevel":1,"nMaxLevel":5,"nXP":100,"bMaxed":null,"strNextLevelName":"Cool Cat","nNextLevelXP":200,"rgCards":[{"strName":"Hinae Arimura","strTitle":"Hinae Arimura","strImgURL":"https://community.akamai.steamstatic.com/economy/image/IzMF03bk9WpSBq-S-ekoE33L-iLqGFHVaU25ZzQNQcXdA3g5gMEPvUZZEfSMJ6dESN8p_2SVTY7V2NAIxHYLmChCIzb02ClFbOttPYDn0gz2tPCMWn36aTDBcnOJRAw_GeVXPDuPqGD2sOmSEzjMFeovQF0BfKdWp2RJbpqOOxJr1o8Vu2u_0UZyDBItYPpPfQ68zylBNehxm3NAfZ8Dmyz4J5GPhFpqPkZrUuzvUrrCPoGmmSktWxwyTvUZesvL7zOq9ZUc_75p9w","strArtworkURL":"https://cdn.akamai.steamstatic.com/steamcommunity/public/images/items/970570/6d419020563a7af12ff7d54cc60dc97456764abd.jpg","strMarketHash":"970570-Hinae Arimura","nOwned":0},{"strName":"Hana Kazuki","strTitle":"Hana Kazuki","strImgURL":"https://community.akamai.steamstatic.com/economy/image/IzMF03bk9WpSBq-S-ekoE33L-iLqGFHVaU25ZzQNQcXdA3g5gMEPvUZZEfSMJ6dESN8p_2SVTY7V2NAIxHYLmChCIzb02ClFZOttc-DH2hDwqKSEEXXwbWqVf3KPSAkwT7NZMWneqjOs57uRR2ubQe16FQgDeqZR8mxMac3aNxVsysdVrCO6mFZ5GwQXe8hHdwrmmHBGZe53mnlGJJlakSX1cJXcjQliaU4-UrzhVu3CbIijmSkiCEsyHL5aOtyD_ijuW07yDiA","strArtworkURL":"https://cdn.akamai.steamstatic.com/steamcommunity/public/images/items/970570/188bdfae8811b3f86eaa9f11967feb97e5a1eba6.jpg","strMarketHash":"970570-Hana Kazuki","nOwned":0},{"strName":"Nono Kurusu","strTitle":"Nono Kurusu","strImgURL":"https://community.akamai.steamstatic.com/economy/image/IzMF03bk9WpSBq-S-ekoE33L-iLqGFHVaU25ZzQNQcXdA3g5gMEPvUZZEfSMJ6dESN8p_2SVTY7V2NAIxHYLmChCIzb02ClDautjc-DT0hDotKSEEXXwbWrBenffGV1sRLBbMTvaqDShsLuRRTqcF-kqFV8Ef6QCp2QYOZuJaxQ6ysdVrCO6mFZ5GwQXe8hHdwrmmHBGZe53mnlGJJlakSX1cJXcjQliaU4-UrzhVu3CbIijmSkiCEsyHL5aOtyD_ijuuVsLcaA","strArtworkURL":"https://cdn.akamai.steamstatic.com/steamcommunity/public/images/items/970570/407de47b7a90b5186e88520e05c69d76412e33dc.jpg","strMarketHash":"970570-Nono Kurusu","nOwned":0},{"strName":"Takuru Miyashiro","strTitle":"Takuru Miyashiro","strImgURL":"https://community.akamai.steamstatic.com/economy/image/IzMF03bk9WpSBq-S-ekoE33L-iLqGFHVaU25ZzQNQcXdA3g5gMEPvUZZEfSMJ6dESN8p_2SVTY7V2NAIxHYLmChCIzb02ClZZO55Kt6N7QzioPGFFWb4Lj7JLibcQVgwT7FWPW_c-WattOXARG6YRex_RwgMKaEE9GRANMiAPkZphtVe_zX2h0p6WBQnYMFDYjCyx3UUNOB3zHRGdplQkSChJJzRhFo0aUNiDLjmXujKa4elwS8nVBxuGaZPNd6WpmWyr4G3Z_V6UCSDjw","strArtworkURL":"https://cdn.akamai.steamstatic.com/steamcommunity/public/images/items/970570/8593fe309b0bf28492ce1ac2798f50789d0a1c0b.jpg","strMarketHash":"970570-Takuru Miyashiro","nOwned":0},{"strName":"Serika Onoe","strTitle":"Serika Onoe","strImgURL":"https://community.akamai.steamstatic.com/economy/image/IzMF03bk9WpSBq-S-ekoE33L-iLqGFHVaU25ZzQNQcXdA3g5gMEPvUZZEfSMJ6dESN8p_2SVTY7V2NAIxHYLmChCIzb02CleYPdlM8qN7wv0pKSEEXXwbWqdenXfSgZuRbNXYG-Mqjql5O3GQ2zNQ755EA8CdPYA-2ZNOciPaxNsysdVrCO6mFZ5GwQXe8hHdwrmmHBGZe53mnlGJJlakSX1cJXcjQliaU4-UrzhVu3CbIijmSkiCEsyHL5aOtyD_iju1vPWBQ0","strArtworkURL":"https://cdn.akamai.steamstatic.com/steamcommunity/public/images/items/970570/43653ce197764b601c83b80d0aa2b226b4024cb1.jpg","strMarketHash":"970570-Serika Onoe","nOwned":0},{"strName":"Uki Yamazoe","strTitle":"Uki Yamazoe","strImgURL":"https://community.akamai.steamstatic.com/economy/image/IzMF03bk9WpSBq-S-ekoE33L-iLqGFHVaU25ZzQNQcXdA3g5gMEPvUZZEfSMJ6dESN8p_2SVTY7V2NAIxHYLmChCIzb02ClYbuwnAcrLwR_0pKSEEXXwbWqQKyCPSAZuGOIPY23c-DOl7bidRT_JQb0rSg9XePFX921OO5uPbBE0ysdVrCO6mFZ5GwQXe8hHdwrmmHBGZe53mnlGJJlakSX1cJXcjQliaU4-UrzhVu3CbIijmSkiCEsyHL5aOtyD_ijulKJpkSg","strArtworkURL":"https://cdn.akamai.steamstatic.com/steamcommunity/public/images/items/970570/61d17a7d5b56bcf9ebd3918b021399be8937825c.jpg","strMarketHash":"970570-Uki Yamazoe","nOwned":0}]}}],["achievementmap",{"version":5,"data":"[]"}],["usernews",{"version":5,"data":[]}],["gameactivity",{"version":5,"data":[]}],["socialmedia",{"version":3,"data":[]}],["associations",{"version":2,"data":{"rgDevelopers":[{"strName":"MAGES. Inc.","strURL":"https://store.steampowered.com/developer/SPIKECHUNSOFT"}],"rgPublishers":[{"strName":"Spike Chunsoft Co., Ltd.","strURL":"https://store.steampowered.com/publisher/SPIKECHUNSOFT"}],"rgFranchises":[{"strName":"Science Adventure Series","strURL":"https://store.steampowered.com/franchise/SciADV"}]}}],["descriptions",{"version":1,"data":{"strFullDescription":"It's been six years since a massive earthquake leveled the city of Shibuya. Now, in October 2015, while researching a number of recent murders, Takuru Miyashiro realizes a horrible truth. These murders are the return of a series of killings that plunged Shibuya into terror six years ago. And at the same time, people called gigalomaniacs, with the powers to make their delusions real, are beginning to awaken...\r\n\r\n[b]GAME FEATURES[/b]\r\n[list][*][b]Discover A Darker Japan[/b]\r\nExplore Shibuya in 2015, after an earthquake nearly levelled the city six years prior, and try to outsmart the puppet-master behind this New Generation Madness.\r\n[*][b]Track Down A Serial Killer[/b]\r\nPlay as Takuru, an arrogant senior and the newspaper club president, and discover the pattern in a series of bizarre deaths around you that the police can't seem to crack.\r\n[*][b]Unravel The Mystery[/b]\r\nInvestigate gruesome, supernatural murders with a team of uniquely talented friends.\r\n[*][b]Pick Your Delusions[/b]\r\nChoose to explore disturbing nightmares or pleasurable daydreams to affect the different realities that Takuru perceives, and change your story.\r\n[*][b]See The Bigger Picture[/b]\r\nUnlock SIX endings by changing the course of your team's investigations and relationships, and understand the characters and plot in depth.\r\n[*][b]Outstanding Artistic Value[/b]\r\nEnjoy beautiful and ethereal art work in this stunning visual novel from the Science Adventure series.\r\n[*][b]From The Creators Of STEINS;GATE[/b]\r\nA stand-alone story with a brand new cast, extensive replayability and ties to the Steins;Gate universe![/list]","strSnippet":"From the creators of the critically acclaimed STEINS;GATE comes a sensational new visual novel: CHAOS;CHILD. Set in Shibuya in 2015, a group of high school students who survived an earthquake six years ago find themselves at the center of a new series of bizarre murders in the city."}}]]